OBP_logging_v5/__init__.py
OBP_logging_v5/cloudwatch.py
OBP_logging_v5/ec2.py
OBP_logging_v5/rds.py
OBP_logging_v5/utils.py
OBP_logging_v5-0.1.2.dist-info/METADATA
OBP_logging_v5-0.1.2.dist-info/WHEEL
OBP_logging_v5-0.1.2.dist-info/top_level.txt
OBP_logging_v5-0.1.2.dist-info/RECORD
